{
  "function_name": "func_0000F15C",
  "asm_text": "nonmatching func_0000F15C, 0x58\n\nglabel func_0000F15C\n    /* DDFBC8 0000F15C 27BDFFD8 */  addiu      $sp, $sp, -0x28\n    /* DDFBCC 0000F160 AFA40028 */  sw         $a0, 0x28($sp)\n    /* DDFBD0 0000F164 AFBF0014 */  sw         $ra, 0x14($sp)\n    /* DDFBD4 0000F168 3C040000 */  lui        $a0, (0x0 >> 16)\n    /* DDFBD8 0000F16C 24840000 */  addiu      $a0, $a0, 0x0\n    /* DDFBDC 0000F170 27A50018 */  addiu      $a1, $sp, 0x18\n    /* DDFBE0 0000F174 0C000000 */  jal        func_00000000\n    /* DDFBE4 0000F178 24060010 */   addiu     $a2, $zero, 0x10\n    /* DDFBE8 0000F17C 27AF0018 */  addiu      $t7, $sp, 0x18\n    /* DDFBEC 0000F180 8DF90000 */  lw         $t9, 0x0($t7)\n    /* DDFBF0 0000F184 8FAE0028 */  lw         $t6, 0x28($sp)\n    /* DDFBF4 0000F188 ADD90000 */  sw         $t9, 0x0($t6)\n    /* DDFBF8 0000F18C 8DF80004 */  lw         $t8, 0x4($t7)\n    /* DDFBFC 0000F190 ADD80004 */  sw         $t8, 0x4($t6)\n    /* DDFC00 0000F194 8DF90008 */  lw         $t9, 0x8($t7)\n    /* DDFC04 0000F198 ADD90008 */  sw         $t9, 0x8($t6)\n    /* DDFC08 0000F19C 8DF8000C */  lw         $t8, 0xC($t7)\n    /* DDFC0C 0000F1A0 ADD8000C */  sw         $t8, 0xC($t6)\n    /* DDFC10 0000F1A4 8FBF0014 */  lw         $ra, 0x14($sp)\n    /* DDFC14 0000F1A8 27BD0028 */  addiu      $sp, $sp, 0x28\n    /* DDFC18 0000F1AC 03E00008 */  jr         $ra\n    /* DDFC1C 0000F1B0 00000000 */   nop\nendlabel func_0000F15C\n",
  "m2c_output": "? func_00000000(?, ? *, ?);                         /* extern */\n\nvoid func_0000F15C(void *arg0) {\n    ? sp18;\n\n    func_00000000(0, &sp18, 0x10);\n    arg0->unk0 = (s32) sp18.unk0;\n    arg0->unk4 = (s32) sp18.unk4;\n    arg0->unk8 = (s32) sp18.unk8;\n    arg0->unkC = (s32) sp18.unkC;\n}\n",
  "attempts": [
    {
      "c_code": "void func_0000F15C(Quad4 *dst) {\n    Quad4 buf;\n    func_00000000(&D_00000000, &buf, 16);\n    *dst = buf;\n}",
      "matched": true,
      "diff_count": 0,
      "diff_details": [],
      "compiler_flags": "",
      "notes": "flags: -O2 -g2"
    }
  ],
  "final_c": "void func_0000F15C(Quad4 *dst) {\n    Quad4 buf;\n    func_00000000(&D_00000000, &buf, 16);\n    *dst = buf;\n}",
  "matched": true,
  "instruction_count": 22,
  "has_branches": false,
  "has_calls": true,
  "timestamp": 1776564853.2201087,
  "game": "glover",
  "compiler": "gcc_2.7.2_kmc",
  "compiler_flags": "-O2 -g2",
  "nearby_decompiled": [],
  "called_functions": [
    "func_00000000"
  ],
  "referenced_data": [],
  "segment": "bootup_uso"
}